<sequence><author><surname>Bar</surname>, Ehrhard <title>- Erläuterungen und Dokumente</title>, <given-names>Johann Wolfgang</given-names></author> <author><surname>Goethe</surname></author>: <title>Wilhelm Meisters Lehrjahre, Reclam</title>, <other>Ditzingen</other> <year>1995</year>.<raw>Bar, Ehrhard - Erläuterungen und Dokumente, Johann Wolfgang Goethe: Wilhelm Meisters Lehrjahre, Reclam, Ditzingen 1995.</raw></sequence><sequence><author><surname>Von Goethe</surname> <given-names>Johann Wolfgang</given-names></author> <author><surname>-</surname></author> <title>Wilhelm Meisters Lehrjahre, Fischer</title>, <other>Frankfurt</other> <year>1999</year>.<raw>Von Goethe, Johann Wolfgang - Wilhelm Meisters Lehrjahre, Fischer, Frankfurt 1999.</raw></sequence><sequence><author><surname>Götze</surname>, <given-names>Martin</given-names></author> <title>- Philosophische Ästhetik - Ästhetische Philosophie, (Teil I und II) Forum for Philosophy and Culture -</title> (<other>1992</other>) - <url>http://www.cogito.de/sicetnon/artikel/kunst/rom1.htm</url><raw>Götze, Martin - Philosophische Ästhetik - Ästhetische Philosophie, (Teil I und II) Forum for Philosophy and Culture - (1992) - http://www.cogito.de/sicetnon/artikel/kunst/rom1.htm</raw></sequence><sequence><author><surname>Novalis -</surname></author> <title>Heinrich von Ofterdingen, Reclam</title>, <other>Ditzingen</other> <year>1987</year>.<raw>Novalis - Heinrich von Ofterdingen, Reclam, Ditzingen 1987.</raw></sequence><sequence><author><surname>Ritzenhoff</surname></author>, Ursula <title>- Erläuterungen und Dokumente, Novalis: Heinrich von Ofterdingen, Reclam</title>, <other>Ditzingen</other> <year>1999</year>.<raw>Ritzenhoff, Ursula - Erläuterungen und Dokumente, Novalis: Heinrich von Ofterdingen, Reclam, Ditzingen 1999.</raw></sequence><sequence><editor>Schulz, Gerhard - Novalis Werke</editor> Hrsg. von <editor>Gerhard Schulz, Beck</editor> <other>München</other> <year>1981</year>.<raw>Schulz, Gerhard - Novalis Werke. Hrsg. von Gerhard Schulz, Beck, München 1981.</raw></sequence>