<sequence><author><surname>Beinhauer</surname>, <given-names>Werner</given-names></author>: <title>Stilistisch-phraseologisches Wörterbuch spanisch-deutsch</title>. <publisher>Max Hueber Verlag</publisher> <year>1978</year>.<raw>Beinhauer, Werner: Stilistisch-phraseologisches Wörterbuch spanisch-deutsch. Max Hueber Verlag. 1978.</raw></sequence><sequence><title>Die Bibel in heutigem Deutsch</title>. <issue>2</issue>. Auflage. <other>Berlin, Altenburg</other> <title>Evangelische Haupt-Bibelgesellschaft zu Berlin und Altenburg</title>. <other>1984</other>.<raw>Die Bibel in heutigem Deutsch. 2. Auflage. Berlin, Altenburg: Evangelische Haupt-Bibelgesellschaft zu Berlin und Altenburg. 1984.</raw></sequence><sequence><author><surname>Burger</surname>, <given-names>Harald</given-names></author>: <title>Idiomatik des Deutschen</title>. <other>Tübingen</other>: <publisher>Max Niemeyer Verlag</publisher> <year>1973</year>.<raw>Burger, Harald: Idiomatik des Deutschen. Tübingen: Max Niemeyer Verlag. 1973.</raw></sequence><sequence><author><surname>Fleischer</surname>, <given-names>Wolfgang</given-names></author>: <title>Phraseologie der deutschen Gegenwartssprache</title>. <other>Leipzig</other>: <publisher>Bibliographisches Institut</publisher> <year>1982</year>.<raw>Fleischer, Wolfgang: Phraseologie der deutschen Gegenwartssprache. Leipzig: Bibliographisches Institut. 1982.</raw></sequence><sequence><author><surname>Kloepfer</surname>, <given-names>Rolf</given-names></author>: <title>Die Theorie der literarischen Übersetzung</title>. <other>München</other>. <year>1967</year>.<raw>Kloepfer, Rolf: Die Theorie der literarischen Übersetzung. München. 1967.</raw></sequence><sequence><author><surname>Dr</surname>. <given-names>Müller</given-names></author>, <title>Heinz/Prof. Dr. Haensch, Günther: Langenscheidts Handwörterbuch Spanisch</title>. <volume>8</volume>. Auflage. <other>Berlin, München</other> <publisher>Langenscheidt KG</publisher> <year>1993</year>.<raw>Dr. Müller, Heinz/Prof. Dr. Haensch, Günther: Langenscheidts Handwörterbuch Spanisch. 8. Auflage. Berlin, München: Langenscheidt KG. 1993.</raw></sequence><sequence><author><surname>Nord</surname>, <given-names>Christiane</given-names></author>: <title>Textanalyse und Übersetzen. Theoretische Grundlagen, Methode und didaktische Anwendung einer übersetzungsrelevanten Textanalyse</title>.<raw>Nord, Christiane: Textanalyse und Übersetzen. Theoretische Grundlagen, Methode und didaktische Anwendung einer übersetzungsrelevanten Textanalyse.</raw></sequence><sequence><editor>Heidelberg</editor>. <year>1988</year>.<raw>Heidelberg. 1988.</raw></sequence><sequence><author><surname>Navarro Ramil</surname> <given-names>Axel Javier</given-names></author> <title>Manuel Vázquez Montalbán auf Deutsch: ein Autor und vier Übersetzer; das Andere in den Zieltexten</title>. <other>Frankfurt am Main</other> <publisher>Peter Lang GmbH</publisher> <year>2000</year>.<raw>Navarro Ramil, Axel Javier: Manuel Vázquez Montalbán auf Deutsch: ein Autor und vier Übersetzer; das Andere in den Zieltexten. Frankfurt am Main: Peter Lang GmbH, 2000.</raw></sequence><sequence><author><surname>Reiß, Katharina/Vermeer</surname> <given-names>Hans J.</given-names></author> <title>Grundlegung einer allgemeinen Translationstheorie</title>. <other>Tübingen. 1984</other><raw>Reiß, Katharina/Vermeer, Hans J.: Grundlegung einer allgemeinen Translationstheorie. Tübingen. 1984.</raw></sequence><sequence><author><surname>Scherer</surname>, <given-names>Hans</given-names></author> <author><surname>Siegfried</surname></author>: <title>Kommentierte Übersetzungen Spanisch-Deutsch: Texte, Wortschatz, Grammatik, Übersetzungskommentare, idiomatische Wendungen</title>. <issue>3</issue>. Auflage. <other>Bonn</other>: <publisher>Romanistischer Verlag</publisher> <year>1993</year>.<raw>Scherer, Hans Siegfried: Kommentierte Übersetzungen Spanisch-Deutsch: Texte, Wortschatz, Grammatik, Übersetzungskommentare, idiomatische Wendungen. 3. Auflage. Bonn: Romanistischer Verlag. 1993.</raw></sequence><sequence><author><surname>Schleiermacher</surname>, <given-names>Friedrich</given-names></author>: <title>Ueber die verschiedenen Methoden des Uebersetzens</title>.<raw>Schleiermacher, Friedrich: Ueber die verschiedenen Methoden des Uebersetzens.</raw></sequence><sequence><year>1838</year>. In: <editor>Störig, H.-J</editor> (Hrsg.), S <fpage>38</fpage> - <lpage>70</lpage>. <year>1973</year>.<raw>1838. In: Störig, H.-J. (Hrsg.), S. 38-70. 1973.</raw></sequence><sequence><author><surname>Schmidt</surname>, <given-names>W</given-names></author>.: <title>Lexikalische und aktuelle Bedeutung. Ein Beitrag zur Theorie der Wortbedeutung</title>. <issue>4</issue>. Auflage. <other>Berlin</other> <year>1967</year>.<raw>Schmidt, W.: Lexikalische und aktuelle Bedeutung. Ein Beitrag zur Theorie der Wortbedeutung. 4. Auflage. Berlin 1967.</raw></sequence><sequence><author><surname>Stolze</surname>, <given-names>Radegundis</given-names></author>: <title>Grundlagen der Textübersetzung</title>. <other>Heidelberg</other>. <year>1982</year>.<raw>Stolze, Radegundis: Grundlagen der Textübersetzung. Heidelberg. 1982.</raw></sequence><sequence><author><surname>Telija</surname>, <given-names>V. N.</given-names></author> <title>Die Phraseologie</title>. In: <source>Allgemeine Sprachwissenschaft</source> Bd.2, S <fpage>374</fpage> - <lpage></lpage>. <other>Berlin</other>. <year>1975</year>.<raw>Telija, V. N.: Die Phraseologie. In: Allgemeine Sprachwissenschaft. Bd.2, S. 374ff. Berlin. 1975.</raw></sequence><sequence><author><surname>Vermeer</surname>, <given-names>Hans J.</given-names></author> <title>voraussetzungen für eine translationstheorie – einige kapitel kultur- und sprachtheorie</title>. <other>Heidelberg</other>. <year>1986</year>.<raw>Vermeer, Hans J.: voraussetzungen für eine translationstheorie – einige kapitel kultur- und sprachtheorie. Heidelberg. 1986.</raw></sequence><sequence><author><surname>Wuthenow</surname>, <given-names>Ralph-Reiner</given-names></author>: <title>Das fremde Kunstwerk</title>. <source>Aspekte der literarischen</source><raw>Wuthenow, Ralph-Reiner: Das fremde Kunstwerk. Aspekte der literarischen</raw></sequence><sequence><author><surname>bersetzung</surname></author>. <other>Göttingen. 1969</other><raw>bersetzung. Göttingen. 1969.</raw></sequence>