<sequence><author><surname>Metzler Literaturlexikon</surname></author> <title>Stichwörter zur Weltliteratur</title> /hrsg. <editor>Von Günther</editor> u. <source>Irmgard Schweikle</source> <other>Stuttgart</other>: <publisher>Metzler</publisher>, <year>1984</year><raw>Metzler Literaturlexikon: Stichwörter zur Weltliteratur /hrsg. Von Günther u. Irmgard Schweikle, Stuttgart: Metzler, 1984</raw></sequence><sequence><author><surname>Christine</surname></author> <title>Lubkoll „Rhythmus und Metrum</title>“ <other>aus: Bosse/Reuter</other> (Hg.): <source>Literaturwissenschaft-Einführung in ein Sprachspiel. Freiburg im</source> <other>Breisgau</other>: <publisher>Rombach,1999</publisher>, <fpage>S</fpage> - <lpage>103</fpage> - <lpage>122</lpage><raw>Christine Lubkoll „Rhythmus und Metrum“ aus: Bosse/Reuter (Hg.): Literaturwissenschaft-Einführung in ein Sprachspiel. Freiburg im Breisgau: Rombach,1999, S.103-122</raw></sequence><sequence><author><surname>Wolfgang</surname> <given-names>Kayser</given-names></author>, „Kleine <author><surname>deutsche</surname> <given-names>Versschule</given-names></author>“, Francke Verlag, Tübingen <year>1995</year><raw>Wolfgang Kayser, „Kleine deutsche Versschule“, Francke Verlag, Tübingen, 1995</raw></sequence><sequence><author><surname>Klaus</surname> <given-names>Weimar</given-names></author>, „<title>Goethes Gedichte 1769-1775</title>“, <source>Interpretationen zu einem Anfang</source> <year>1982</year><raw>Klaus Weimar, „Goethes Gedichte 1769-1775“, Interpretationen zu einem Anfang, 1982</raw></sequence><sequence><author><surname>Oldenbourg</surname> <given-names>Interpretationen</given-names></author>; „<title>Gedichte der Empfindsamkeit und des Sturm und Drang“, Interpetiert von: Dagmar Schuster und Bernd</title> Sowinski, <year>1992</year><raw>Oldenbourg Interpretationen; „Gedichte der Empfindsamkeit und des Sturm und Drang“, Interpetiert von: Dagmar Schuster und Bernd Sowinski, 1992</raw></sequence><sequence><author><surname>Karl</surname> <given-names>Otto Conrady</given-names></author> Goethe- <source>Leben und Werk</source> <year>1994</year> Artemis & <publisher>Winkler Verlag</publisher> <other>München</other> und <other>Zürich</other><raw>Karl Otto Conrady, Goethe- Leben und Werk, 1994 Artemis & Winkler Verlag, München und Zürich</raw></sequence>