<sequence><author><surname>Dürrenmatt</surname>, <given-names>Friedrich</given-names></author>: <title>Die Physiker</title>. <source>Komödie, Zürich</source> <year>1980</year><raw>Dürrenmatt, Friedrich: Die Physiker. Komödie, Zürich 1980</raw></sequence><sequence><author><surname>Dürrenmatt</surname>, <given-names>Friedrich</given-names></author>: <title>Der Besuch der alten Dame</title>. <source>Tragische Komödie, Zürich</source> <year>1998</year><raw>Dürrenmatt, Friedrich: Der Besuch der alten Dame. Tragische Komödie, Zürich 1998</raw></sequence><sequence><author><surname>Dürrenmatt</surname>, <given-names>Friedrich</given-names></author>: <title>Romulus der Große. Ungeschichtliche historische</title> <source>Komödie, Zürich</source> <year>1998</year><raw>Dürrenmatt, Friedrich: Romulus der Große. Ungeschichtliche historische Komödie, Zürich 1998</raw></sequence><sequence><editor>Dürrenmatt, Friedrich: Der Meteor</editor> / <source>Dichterdämmerung. Nobelpreisträgerstücke, Zürich</source> <year>1998</year><raw>Dürrenmatt, Friedrich: Der Meteor / Dichterdämmerung. Nobelpreisträgerstücke, Zürich 1998</raw></sequence><sequence><author><surname>Dürrenmatt</surname>, <given-names>Friedrich</given-names></author>: <title>Ein Engel kommt nach Babylon</title>. <source>Fragmentarische Komödie, Zürich</source> <year>1998</year><raw>Dürrenmatt, Friedrich: Ein Engel kommt nach Babylon. Fragmentarische Komödie, Zürich 1998</raw></sequence><sequence><author><surname>Dürrenmatt</surname>, <given-names>Friedrich</given-names></author>: <title>Der Richter und sein Henker</title>. <other>Roman, Zürich</other> <year>1966</year><raw>Dürrenmatt, Friedrich: Der Richter und sein Henker. Roman, Zürich 1966</raw></sequence><sequence><author><surname>Dürrenmatt</surname>, <given-names>Friedrich</given-names></author>: <title>Die Panne. Hörspiel und Komödie</title>, <other>Zürich</other> <year>1985</year><raw>Dürrenmatt, Friedrich: Die Panne. Hörspiel und Komödie, Zürich 1985</raw></sequence><sequence><author><surname>Dürrenmatt</surname>, <given-names>Friedrich</given-names></author>: <title>Theaterprobleme</title> In: <source>Ebd.: Theater. Essays, Gedichte, Reden, Zürich</source> <year>1998</year><raw>Dürrenmatt, Friedrich: Theaterprobleme. In: Ebd.: Theater. Essays, Gedichte, Reden, Zürich 1998</raw></sequence><sequence><author><surname>Arnold</surname>, <given-names>Heinz</given-names></author> <author><surname>Ludwig</surname></author>: <title>Theater als Abbild der labyrinthischen Welt. Versuch über den Dramatiker Dürrenmatt</title>. In: Ebd.(Hg.) <source>Text + Kritik. Zeitschrift für Literatur. Heft 50/51. Friedrich Dürrenmatt I</source> <other>München</other> <year>19802</year><raw>Arnold, Heinz Ludwig: Theater als Abbild der labyrinthischen Welt. Versuch über den Dramatiker Dürrenmatt. In: Ebd.(Hg.): Text + Kritik. Zeitschrift für Literatur. Heft 50/51. Friedrich Dürrenmatt I, München 19802</raw></sequence><sequence><author><surname>Beutin</surname>, <given-names>Wolfgang/U.a.: Deutsche</given-names></author> <title>Literaturgeschichte. Von den Anfängen bis zur Gegenwart</title>, <other>Stuttgart</other> <year>19945</year><raw>Beutin, Wolfgang/U.a.: Deutsche Literaturgeschichte. Von den Anfängen bis zur Gegenwart, Stuttgart 19945</raw></sequence><sequence><author><surname>Dittberner</surname>, <given-names>Hugo</given-names></author>: <title>Dürenmatt, der Geschichtenerzähler. Ein 50-Dollar-Mißverständnis zum „Besuch der alten Dame</title>“. In: <editor>Arnold, Heinz Ludwig</editor> (Hg.): <source>Text + Kritik. Zeitschrift für Literatur. Heft 50/51. Friedrich Dürrenmatt I</source> <other>München</other> <year>19802</year><raw>Dittberner, Hugo: Dürenmatt, der Geschichtenerzähler. Ein 50-Dollar-Mißverständnis zum „Besuch der alten Dame“. In: Arnold, Heinz Ludwig (Hg.): Text + Kritik. Zeitschrift für Literatur. Heft 50/51. Friedrich Dürrenmatt I, München 19802</raw></sequence><sequence><author><surname>Eisenbeis</surname>, <given-names>Manfred</given-names></author>: <title>Lektürehilfen. Friedrich Dürrenmatt. Die Physiker</title>, <other>Stuttgart</other> <year>200410</year><raw>Eisenbeis, Manfred: Lektürehilfen. Friedrich Dürrenmatt. Die Physiker, Stuttgart 200410</raw></sequence><sequence><author><surname>Jenny</surname>, <given-names>Urs</given-names></author>: <title>Friedrich Dürrenmatt</title>, <other>Hannover</other> <year>1965</year><raw>Jenny, Urs: Friedrich Dürrenmatt, Hannover 1965</raw></sequence><sequence><author><surname>Knapp</surname>, <given-names>Gerhard P.</given-names></author> <title>Friedrich Dürrenmatt</title>, <other>Stuttgart</other> <year>19932</year><raw>Knapp, Gerhard P.: Friedrich Dürrenmatt, Stuttgart 19932</raw></sequence><sequence><author><surname>Koch</surname> <given-names>Roland/Koch</given-names></author> <author><surname>Ute</surname></author>: <title>Kleine Literaturgeschichte im Überblick</title>, <other>Mannheim</other> <year>19922</year><raw>Koch Roland/Koch Ute: Kleine Literaturgeschichte im Überblick, Mannheim 19922</raw></sequence><sequence><author><surname>Krättli</surname>, <given-names>Anton</given-names></author>: <title>Friedrich Dürrenmatt</title>. In: <editor>Arnold, Heinz Ludwig</editor> (Hg.): <source>Kritisches Lexikon zur deutschsprachigen Gegenwartsliteratur</source> Band <volume>3</volume>, <other>München 1978ff</other><raw>Krättli, Anton: Friedrich Dürrenmatt. In: Arnold, Heinz Ludwig (Hg.): Kritisches Lexikon zur deutschsprachigen Gegenwartsliteratur. Band 3, München 1978ff</raw></sequence><sequence><author><surname>Kurzenberger</surname>, <given-names>Hajo</given-names></author>: <title>Theater der Realität als Realität des Theaters. Zu Friedrich Dürrenmatts Dramenkonzeption</title>. In: <editor>Arnold, Heinz Ludwig</editor> (Hg.): <source>Text + Kritik. Zeitschrift für Literatur. Heft 50/51. Friedrich Dürrenmatt I</source> <other>München</other> <year>19802</year><raw>Kurzenberger, Hajo: Theater der Realität als Realität des Theaters. Zu Friedrich Dürrenmatts Dramenkonzeption. In: Arnold, Heinz Ludwig (Hg.): Text + Kritik. Zeitschrift für Literatur. Heft 50/51. Friedrich Dürrenmatt I, München 19802</raw></sequence><sequence><author><surname>Profitlich</surname>, <given-names>Ulrich</given-names></author>: <title>Friedrich Dürrenmatt</title>. In: <editor>Von Wiese, Benno</editor> (Hg.): <source>Deutsche Dichter der Gegenwart. Ihr Leben und Werk</source> <other>Berlin</other> <year>1973</year><raw>Profitlich, Ulrich: Friedrich Dürrenmatt. In: Von Wiese, Benno (Hg.): Deutsche Dichter der Gegenwart. Ihr Leben und Werk, Berlin 1973</raw></sequence><sequence><author><surname>Pulver</surname>, <given-names>Elsbeth</given-names></author>: <title>Literaturtheorie und Politik. Zur Dramaturgie Friedrich Dürrenmatts</title>. In: <editor>Arnold, Heinz Ludwig</editor> (Hg.): <source>Text + Kritik. Zeitschrift für Literatur. Heft 50/51. Friedrich Dürrenmatt I</source> <other>München</other> <year>19802</year><raw>Pulver, Elsbeth: Literaturtheorie und Politik. Zur Dramaturgie Friedrich Dürrenmatts. In: Arnold, Heinz Ludwig (Hg.): Text + Kritik. Zeitschrift für Literatur. Heft 50/51. Friedrich Dürrenmatt I, München 19802</raw></sequence><sequence><author><surname>Von Einsiedel</surname></author> <title>Wolfgang/Woerner, Gert/Geisler, Rolf/Radler, Rudolf/U.a.: Kindlers Literatur Lexikon. Im dtv</title>, <other>München</other> <year>1986</year>. [SÄMTLICHE BÄNDE]<raw>Von Einsiedel, Wolfgang/Woerner, Gert/Geisler, Rolf/Radler, Rudolf/U.a.: Kindlers Literatur Lexikon. Im dtv, München 1986. [SÄMTLICHE BÄNDE]</raw></sequence>