<sequence><url>http://www.br- online.de/jugend/izi/text/kuebler14_2.pdf</url><raw>http://www.br- online.de/jugend/izi/text/kuebler14_2.pdf</raw></sequence><sequence><url>http://www.t0.or.at/~kdobl/diss/lingerw.htm</url><raw>http://www.t0.or.at/~kdobl/diss/lingerw.htm</raw></sequence><sequence><url>http://lbs.bw.schule.de/onmerz</url><raw>http://lbs.bw.schule.de/onmerz</raw></sequence><sequence><url>http://www.uni-essen.de/linguistik.buenting/varietaetenscript1.pdf</url><raw>http://www.uni-essen.de/linguistik.buenting/varietaetenscript1.pdf</raw></sequence><sequence><editor>Fernsehsender: KiKa, ZDF, NDR</editor> und <author><surname>HR</surname></author><raw>Fernsehsender: KiKa, ZDF, NDR und HR</raw></sequence>