<sequence><author><surname>von</surname> <given-names>Goethe</given-names></author>, <author><surname>Johann Wolfgang</surname></author> <title>Die Leiden des jungen Werther</title>, in <editor>Rikman, Anna</editor> (Hrsg.): <source>Die Leiden des jungen Werther. Text und Kontext. Reclam</source> <other>Ditzingen</other>. <year>2015</year><raw>von Goethe, Johann Wolfgang: Die Leiden des jungen Werther, in Rikman, Anna (Hrsg.): Die Leiden des jungen Werther. Text und Kontext. Reclam, Ditzingen. 2015</raw></sequence>