<sequence><editor>Eisenmann</editor> <year>2013</year>): <title>Barbara Eisenmann: Erzählen in der Therapie. Eine Untersuchung aus handlungstheoretischer und psychoanalytischer Perspektive</title>. <other>Opladen</other>, <publisher>Westdeutscher Verlag</publisher> <year>2013</year>.<raw>Eisenmann 2013): Barbara Eisenmann: Erzählen in der Therapie. Eine Untersuchung aus handlungstheoretischer und psychoanalytischer Perspektive. Opladen, Westdeutscher Verlag 2013.</raw></sequence><sequence><author><surname>Ende</surname></author> <year>1973</year>): <title>Michael Ende: Momo. Thienemann</title>, <other>Stuttgart</other> <year>1973</year>.<raw>Ende 1973): Michael Ende: Momo. Thienemann, Stuttgart 1973.</raw></sequence><sequence><author><surname>Fallaci</surname></author> <year>1977</year>): <title>Oriana Fallaci: Brief an ein nie geborenes Kind. Goverts</title>, <other>Frankfurt</other> <year>1977</year>.<raw>Fallaci 1977): Oriana Fallaci: Brief an ein nie geborenes Kind. Goverts, Frankfurt 1977.</raw></sequence><sequence><author><surname>Fallaci</surname></author> <year>1975</year>): <title>Oriana Fallaci: Lettera a un bambino mai nato. Rizzoli</title>, <other>Milano 1075</other><raw>Fallaci 1975): Oriana Fallaci: Lettera a un bambino mai nato. Rizzoli, Milano 1075.</raw></sequence><sequence><editor>Förtsch</editor> <year>2017</year>): <title>David Förtsch: Der postmoderne Roman und die Autorin Raya Mann</title>. <other>München</other>, <publisher>GRIN Verlag</publisher> <year>2017</year>. <url>https://www.grin.com/document/375729</url><raw>Förtsch 2017): David Förtsch: Der postmoderne Roman und die Autorin Raya Mann. München, GRIN Verlag 2017. https://www.grin.com/document/375729</raw></sequence><sequence><author><surname>Grabbe</surname></author> <year>2005</year>): <title>Katharina Grabbe: Geschwisterliebe. Verbotenes Begehren in literarischen Texten der Gegenwart. Aisthesis</title>, <other>Bielefeld</other> <year>2005</year>.<raw>Grabbe 2005): Katharina Grabbe: Geschwisterliebe. Verbotenes Begehren in literarischen Texten der Gegenwart. Aisthesis, Bielefeld 2005.</raw></sequence><sequence><editor>Grauzone</editor> <year>1981</year>): <title>Martin Eicher: Eisbär. Off Course Music</title>, Saas Fee <year>1981</year>.<raw>Grauzone 1981): Martin Eicher: Eisbär. Off Course Music, Saas Fee 1981.</raw></sequence><sequence><author><surname>Grimm</surname></author> <year>1812</year>): <title>Jacob Grimm, Wilhelm Grimm: Kinder- und Hausmärchen</title> Band <volume>1</volume>. <editor>Georg Andreas Reimer</editor> <other>Berlin</other> <year>1812</year>.<raw>Grimm 1812): Jacob Grimm, Wilhelm Grimm: Kinder- und Hausmärchen Band 1. Georg Andreas Reimer, Berlin 1812.</raw></sequence><sequence><editor>Irving</editor> <year>1985</year>): <title>John Irving: The Cider House Rules</title>. <other>Morrow, New York</other> <year>1985</year>.<raw>Irving 1985): John Irving: The Cider House Rules. Morrow, New York 1985.</raw></sequence><sequence><editor>Irving</editor> <year>1981</year>): <title>John Irving: The Hotel New Hampshire</title>. E. P. Dutton, Boston <year>1981</year>.<raw>Irving 1981): John Irving: The Hotel New Hampshire. E. P. Dutton, Boston 1981.</raw></sequence><sequence><editor>Irving</editor> <year>1988</year>): <title>John Irving: Gottes Werk und Teufels Beitrag</title>. <source>Diogenes, Zürich</source> <year>1988</year>.<raw>Irving 1988): John Irving: Gottes Werk und Teufels Beitrag. Diogenes, Zürich 1988.</raw></sequence><sequence><author><surname>Kierkegaard</surname></author> <year>1991</year>): <title>Sören Kierkegaard: Der Begriff Angst</title>. <source>Gesammelte Werke</source> Band <volume>10</volume>. Gütersloher Verlagshaus, Gütersloh <year>1991</year>.<raw>Kierkegaard 1991): Sören Kierkegaard: Der Begriff Angst. Gesammelte Werke Band 10. Gütersloher Verlagshaus, Gütersloh 1991.</raw></sequence><sequence><author><surname>Lobsien</surname></author> <year>2012</year>): <title>Eckhard Lobsien: Schematisierte Ansichten. Literaturtheorie mit Husserl, Ingarden</title>, <other>Blumenberg. Wilhelm Fink, München</other> <year>2012</year>.<raw>Lobsien 2012): Eckhard Lobsien: Schematisierte Ansichten. Literaturtheorie mit Husserl, Ingarden, Blumenberg. Wilhelm Fink, München 2012.</raw></sequence><sequence><author><surname>Luhmann</surname></author> <year>1994</year>): <title>Niklas Luhmann: Liebe als Passion. Zur Codierung von Intimität. Suhrkamp</title>, <other>Berlin</other> <year>1994</year>.<raw>Luhmann 1994): Niklas Luhmann: Liebe als Passion. Zur Codierung von Intimität. Suhrkamp, Berlin 1994.</raw></sequence><sequence><title>Köppe und Kindt 2014): Tilmann Köppe, Tom Kindt: Erzähltheorie. Eine Einführung. Reclam</title>, <other>Leipzig</other> <year>2014</year>.<raw>Köppe und Kindt 2014): Tilmann Köppe, Tom Kindt: Erzähltheorie. Eine Einführung. Reclam, Leipzig 2014.</raw></sequence><sequence><title>Köppe und Winko 2013): Tilman Köppe und Simone Winko: Neuere Literaturtheorien. Metzler</title>, <other>Weimar</other> <year>2013</year>.<raw>Köppe und Winko 2013): Tilman Köppe und Simone Winko: Neuere Literaturtheorien. Metzler, Weimar 2013.</raw></sequence><sequence><author><surname>Mann</surname></author> <year>1921</year>): <title>Thomas Mann: Wälsungenblut. Phantasus</title>, <other>München</other> <year>1921</year>.<raw>Mann 1921): Thomas Mann: Wälsungenblut. Phantasus, München 1921.</raw></sequence><sequence><author><surname>Mann</surname></author> <year>2018</year>): <title>Raya Mann: Seltene Mädchen. Epubli</title>, <other>Berlin</other> <year>2018</year>.<raw>Mann 2018): Raya Mann: Seltene Mädchen. Epubli, Berlin 2018.</raw></sequence><sequence><author><surname>McEwan</surname></author> <year>1978</year>): <title>Ian McEwan: The Cement Garden</title>. <other>Jonathan Cape, London</other> <year>1978</year>.<raw>McEwan 1978): Ian McEwan: The Cement Garden. Jonathan Cape, London 1978.</raw></sequence><sequence><author><surname>Mercier</surname></author> <year>1998</year>): <title>Pascal Mercier: Der Klavierstimmer</title>. Knaus, <other>München</other>, <year>1998</year>.<raw>Mercier 1998): Pascal Mercier: Der Klavierstimmer. Knaus, München, 1998.</raw></sequence><sequence><author><surname>Musil</surname></author> <year>1943</year>): <title>Robert Musil: Der Mann ohne Eigenschaften</title> Band <volume>3</volume>. <other>Rowohlt, Lausanne</other> <year>1943</year>.<raw>Musil 1943): Robert Musil: Der Mann ohne Eigenschaften Band 3. Rowohlt, Lausanne 1943.</raw></sequence><sequence><author><surname>von Hoff</surname></author> <year>2003</year>): <title>Dagmar von Hoff: Familiengeheimnisse. Inzest in Literatur und Film der Gegenwart</title>. <other>Böhlau, Köln</other> <year>2003</year>.<raw>von Hoff 2003): Dagmar von Hoff: Familiengeheimnisse. Inzest in Literatur und Film der Gegenwart. Böhlau, Köln 2003.</raw></sequence>