<sequence><author><surname>Illies</surname>, <given-names>Florian</given-names></author>: <title>Generation Golf. Eine Inspektion</title>. <volume>13</volume>. Aufl. S. Fischer <other>Frankfurt am Main</other> <year>2011</year>.<raw>Illies, Florian: Generation Golf. Eine Inspektion. 13. Aufl. S. Fischer, Frankfurt am Main 2011.</raw></sequence><sequence><author><surname>Kracht</surname>, <given-names>Christian: Faserland</given-names></author> (<year>1995</year>), <volume>4</volume>. <title>Auflage</title> <other>Frankfurt am Main</other> S. Fischer <year>2015</year>.<raw>Kracht, Christian: Faserland (1995), 4. Auflage, Frankfurt am Main, S. Fischer, 2015.</raw></sequence><sequence><author><surname>Salinger</surname>, <given-names>Jerome</given-names></author> <author><surname>David</surname></author>: <title>Der Fänger im Roggen (1951), neuübers. von Eike Schönfeld</title>, 11. Auflage <other>Reinbek bei Hamburg</other> <year>2010</year>.<raw>Salinger, Jerome David: Der Fänger im Roggen (1951), neuübers. von Eike Schönfeld, 11. Auflage, Reinbek bei Hamburg, 2010.</raw></sequence><sequence><author><surname>Baßler</surname>, <given-names>Moritz</given-names></author>: <title>Der deutsche Pop-Roman. Die neuen Archivisten</title>. <editor>C.H. Beck</editor> <other>München</other>, <year>2002</year>.<raw>Baßler, Moritz: Der deutsche Pop-Roman. Die neuen Archivisten. C.H. Beck, München, 2002.</raw></sequence><sequence><author><surname>Baßler</surname>, <given-names>Moritz</given-names></author>: <title>Deutsche Erzählprosa 1850-1950. Eine Geschichte literarischer Verfahren</title>. <other>Berlin, Erich Schmidt</other> <publisher>Verlag</publisher>, <year>2015</year>.<raw>Baßler, Moritz: Deutsche Erzählprosa 1850-1950. Eine Geschichte literarischer Verfahren. Berlin, Erich Schmidt Verlag, 2015.</raw></sequence><sequence><author><surname>Beuse</surname>, <given-names>Stefan</given-names></author>: <title>154 schöne weiße leere Blätter. Christian Krachts „Faserland</title>“ (<year>1995</year>). In: <editor>Der deutsche Roman der Gegenwart</editor> Hrsg. von <editor>Wieland</editor> & <editor>Winfried Freund</editor> <other>München</other>: <publisher>Wilhelm Fink Verlag</publisher> <other>München</other>, <year>2001</year>. S. <fpage>150</fpage> - <lpage>155</lpage>.<raw>Beuse, Stefan: 154 schöne weiße leere Blätter. Christian Krachts „Faserland“ (1995). In: Der deutsche Roman der Gegenwart. Hrsg. von Wieland & Winfried Freund. München: Wilhelm Fink Verlag, München, 2001. S. 150-155.</raw></sequence><sequence><author><surname>Diederichsen</surname>, <given-names>Diedrich</given-names></author>: „<title>Pop – deskriptiv, normativ, emphatisch</title>” (<year>1996</year>) <title>und „Ist was, Pop</title>?“ (<year>1999</year>) in: <editor>Charis Goer, Stefan Greif, Christoph Jacke</editor> (Hrsg.): <source>Texte zur Theorie des Pop</source> <other>Stuttgart</other>: <publisher>Reclam</publisher>, <year>2013</year>.<raw>Diederichsen, Diedrich: „Pop – deskriptiv, normativ, emphatisch” (1996) und „Ist was, Pop?“ (1999) in: Charis Goer, Stefan Greif, Christoph Jacke (Hrsg.): Texte zur Theorie des Pop. Stuttgart: Reclam, 2013.</raw></sequence><sequence><author><surname>Hasbach</surname>, <given-names>Claudia: Christian</given-names></author> <title>Krachts „Faserland“ im Kontext der neuen deutschen Popliteratur</title>. <other>Düsseldorf</other> <year>2010</year>.<raw>Hasbach, Claudia: Christian Krachts „Faserland“ im Kontext der neuen deutschen Popliteratur. Düsseldorf 2010.</raw></sequence><sequence><author><surname>Hecken</surname>, <given-names>Thomas</given-names></author>: <title>Pop.Geschichte eines Konzepts. 1955-2009</title>. <other>Bielefeld</other>, <publisher>transcript Verlag</publisher> <year>2009</year>.<raw>Hecken, Thomas: Pop.Geschichte eines Konzepts. 1955-2009. Bielefeld, transcript Verlag, 2009.</raw></sequence><sequence><author><surname>Jugendliche</surname></author> <title>Lebenswelten im Spiegel der deutschsprachigen Popliteratur seit den 1990er Jahren</title>, in: <source>Mitteilungen des Deutschen Germanistenverbandes</source> <volume>55</volume> (<year>2008</year>), H. <issue>2</issue>: <title>Literatur im 21. Jahrhundert</title>, S. <fpage>120</fpage> - <lpage>142</lpage>.<raw>Jugendliche Lebenswelten im Spiegel der deutschsprachigen Popliteratur seit den 1990er Jahren, in: Mitteilungen des Deutschen Germanistenverbandes 55 (2008), H. 2: Literatur im 21. Jahrhundert, S. 120-142.</raw></sequence><sequence><author><surname>Kendel</surname>, <given-names>Konstanze</given-names></author> <author><surname>Maria</surname></author>: <title>Let me entertain you! Die Inszenierung der Popliteratur im Literaturbetrieb der Gegenwart</title> in: <source>Materialien und Ergebnisse aus Forschungsprojekten des Instituts Heft</source> <volume>17</volume>, <other>Bremen</other>, <year>2005</year>.<raw>Kendel, Konstanze Maria: Let me entertain you! Die Inszenierung der Popliteratur im Literaturbetrieb der Gegenwart in: Materialien und Ergebnisse aus Forschungsprojekten des Instituts Heft 17, Bremen, 2005.</raw></sequence><sequence><author><surname>Obst</surname>, <given-names>Helmut</given-names></author>: <title>Der deutsche Pop-Roman und die Postmoderne seit 1990. Dargestellt an Erzählprosa von Christian Kracht, Benjamin von Stuckrad-Barre und Benjamin Lebert</title>. <other>Stuttgart</other>, <year>2002</year>.<raw>Obst, Helmut: Der deutsche Pop-Roman und die Postmoderne seit 1990. Dargestellt an Erzählprosa von Christian Kracht, Benjamin von Stuckrad-Barre und Benjamin Lebert. Stuttgart, 2002.</raw></sequence><sequence><author><surname>Paulokat</surname>, <given-names>Ute, Degler/ Frank</given-names></author> <title>Neue Deutsche Popliteratur</title>, <other>Paderborn; Stuttgart</other> <publisher>Fink Verlag</publisher> <year>2008</year>.<raw>Paulokat, Ute, Degler/ Frank: Neue Deutsche Popliteratur, Paderborn; Stuttgart, Fink Verlag, 2008.</raw></sequence><sequence><title>berquert die Grenzen, schließt den</title> <author><surname>Graben</surname></author>! (<year>1968</year>): <title>Das Zeitalter der neuen Literatur. Die Wieder-Geburt der Kritik</title>. In: <source>Christ und Welt (13. 09</source> <year>1968</year> +) <title>Das Zeitalter der neuen Literatur. Indianer, Science Fiction und Pornographie</title>. In: <source>Christ und Welt (20. 09</source> <year>1968</year>).<raw>berquert die Grenzen, schließt den Graben! (1968): Das Zeitalter der neuen Literatur. Die Wieder-Geburt der Kritik. In: Christ und Welt (13. 09. 1968) + Das Zeitalter der neuen Literatur. Indianer, Science Fiction und Pornographie. In: Christ und Welt (20. 09. 1968).</raw></sequence><sequence><publisher>Presse</publisher><raw>Presse</raw></sequence><sequence><author><surname>Diez</surname>, <given-names>Georg: Christian</given-names></author> <author><surname>Kracht</surname></author>: <title>Faserland. Frankfurter Allgemeine Zeitung</title>. <other>17. März</other> <year>2002</year>.<raw>Diez, Georg: Christian Kracht: Faserland. Frankfurter Allgemeine Zeitung. 17. März 2002.</raw></sequence><sequence>fis: <title>Faserland hat das Zeug zum deutschen Kultbuch der 90er</title>. In: <source>Frankfurter Neue Presse</source> <volume>5</volume>. <year>April 1995</year><raw>fis: Faserland hat das Zeug zum deutschen Kultbuch der 90er. In: Frankfurter Neue Presse, 5. April 1995.</raw></sequence><sequence><author><surname>Halter</surname>, <given-names>Martin</given-names></author> in: <editor>Tages-Anzeiger, Zürich</editor> <other>vom 29. April</other> <year>1995</year>.<raw>Halter, Martin in: Tages-Anzeiger, Zürich, vom 29. April 1995.</raw></sequence><sequence><author><surname>Steinert</surname>, <given-names>Hajo</given-names></author>: <title>Dandy, Schnösel oder Ekel</title>, in: <source>Die Weltwoche vom 30. März</source> <year>1995</year>.<raw>Steinert, Hajo: Dandy, Schnösel oder Ekel, in: Die Weltwoche vom 30. März 1995.</raw></sequence><sequence><author><surname>Junge</surname></author> <title>Hühner, alte Hasen</title>. In: <other>Stern 11 November 1995</other><raw>Junge Hühner, alte Hasen. In: Stern 11 November 1995.</raw></sequence><sequence><author><surname>Kracht</surname>, <given-names>Christian</given-names></author>: <title>Ich denke immer an den Krieg, Interview mit der Zeitschrift</title> <other>Neon, Oktober</other> <year>2008</year>.<raw>Kracht, Christian: Ich denke immer an den Krieg, Interview mit der Zeitschrift Neon, Oktober 2008.</raw></sequence><sequence><publisher>Internetquellen</publisher><raw>Internetquellen</raw></sequence><sequence><author><surname>Weber</surname>, <given-names>Stefanie</given-names></author>: <title>Der Bildungsroman im Zeitalter der Pop-Literatur</title>. <other>Wolfgang Herrndorf</other> und <editor>Christian Kracht</editor> <other>München</other>, <publisher>GRIN Verlag</publisher> <year>2016</year>. <url>https://www.grin.com/document/351339</url><raw>Weber, Stefanie: Der Bildungsroman im Zeitalter der Pop-Literatur. Wolfgang Herrndorf und Christian Kracht, München, GRIN Verlag, 2016. https://www.grin.com/document/351339</raw></sequence><sequence><url>https://www.youtube.com/watch?v=Y3036n9hTXU</url> ab 7:25min, abgerufen am <other>21.08.2019</other><raw>https://www.youtube.com/watch?v=Y3036n9hTXU ab 7:25min, abgerufen am 21.08.2019</raw></sequence><sequence><url>https://www.zeit.de/1999/37/199937.reden_stuckrad_k.xml</url> , abgerufen am <other>04.06.2019</other><raw>https://www.zeit.de/1999/37/199937.reden_stuckrad_k.xml , abgerufen am 04.06.2019</raw></sequence><sequence><url>https://www.faz.net/aktuell/feuilleton/buecher/rezensionen/belletristik/rezension-belletristik-christian-kracht-faserland-152146.html</url><raw>https://www.faz.net/aktuell/feuilleton/buecher/rezensionen/belletristik/rezension-belletristik-christian-kracht-faserland-152146.html</raw></sequence>