<sequence><publisher>PRIMÄRLITERATUR</publisher><raw>PRIMÄRLITERATUR</raw></sequence><sequence><author><surname>Valle-Inclán</surname></author>, Ramón del:Sonatas,Colección Austral<raw>Valle-Inclán, Ramón del:Sonatas,Colección Austral,</raw></sequence><sequence><title>Decimosexta edición (primera edición 1944</title>), Madrid <year>1989</year>.<raw>Decimosexta edición (primera edición 1944), Madrid 1989.</raw></sequence><sequence><publisher>SEKUNDÄRLITERATUR</publisher><raw>SEKUNDÄRLITERATUR</raw></sequence><sequence><author><surname>Alonso</surname>, <given-names>Amado</given-names></author>: "<title>Estructura de las «Sonatas» de Valle- Inclán", in:Ramón del Valle-Inclán</title>, hrsg.v. Ricardo Doménech, Taurus, Madrid <year>1988</year>.<raw>Alonso, Amado: "Estructura de las «Sonatas» de Valle- Inclán", in:Ramón del Valle-Inclán, hrsg.v. Ricardo Doménech, Taurus, Madrid 1988.</raw></sequence><sequence><author><surname>Bernhofer</surname>, <given-names>Martin:Valle-Inclán</given-names></author> <title>und die spanische Kultur im silbernen Zeitalter, Wiss</title>. <source>Buchges</source>., <other>Darmstadt</other> <year>1992</year><raw>Bernhofer, Martin:Valle-Inclán und die spanische Kultur im silbernen Zeitalter, Wiss. Buchges., Darmstadt 1992</raw></sequence><sequence><author><surname>Constantinescu-Iasi</surname>, <given-names>Ioan</given-names></author>: "<title>El burlador auf der Bühne. Zur literarischen und szenischen Interpretation der Don-Juan- Figur", in:Cahiers d'histoire des Littératures Romanes</title> / <source>Romanistische Zeitschrift für Literaturgeschichte</source> <other>hrsg.v</other>. <publisher>Henning Kraus, Universitätsverl.C.Winter</publisher> <other>Heidelberg</other> <year>1997</year>.<raw>Constantinescu-Iasi, Ioan: "El burlador auf der Bühne. Zur literarischen und szenischen Interpretation der Don-Juan- Figur", in:Cahiers d'histoire des Littératures Romanes / Romanistische Zeitschrift für Literaturgeschichte, hrsg.v. Henning Kraus, Universitätsverl.C.Winter, Heidelberg 1997.</raw></sequence><sequence><author><surname>Gibbs</surname>, <given-names>Virginia:Las</given-names></author> <title>Sonatas de Valle-Inclán: kitsch, sexualidad, satanismo, historia,Editorial Pliegos</title>, <other>Madrid</other>. <year>1993</year>.<raw>Gibbs, Virginia:Las Sonatas de Valle-Inclán: kitsch, sexualidad, satanismo, historia,Editorial Pliegos, Madrid. 1993.</raw></sequence><sequence><author><surname>Habermas</surname>, <given-names>Jürgen:Nachmetaphysisches</given-names></author> <title>Denken, Philosophische Aufsätze, Suhrkamp</title>, <other>Frankfurt</other> <year>1992</year>.<raw>Habermas, Jürgen:Nachmetaphysisches Denken, Philosophische Aufsätze, Suhrkamp, Frankfurt 1992.</raw></sequence><sequence><author><surname>Don Juan</surname></author> <title>Darstellung und Deutung,hrsg.v. Brigitte Wittmann, Wiss.Buchges</title>., <other>Darmstadt</other> <year>1976</year>.<raw>Don Juan, Darstellung und Deutung,hrsg.v. Brigitte Wittmann, Wiss.Buchges., Darmstadt 1976.</raw></sequence><sequence><author><surname>Hinterhäuser</surname>, <given-names>Hans:Fin</given-names></author> <title>de siècle, Gestalten und Mythen</title>, <other>Wilhelm</other> <publisher>Fink Verlag</publisher> <other>München</other> <year>1977</year>.<raw>Hinterhäuser, Hans:Fin de siècle, Gestalten und Mythen, Wilhelm Fink Verlag, München 1977.</raw></sequence><sequence><author><surname>Lopez</surname></author>, <title>Ignacio-Javier:Caballero de Novela, Ensayo sobre el donjuanismo en la novela española moderna, 1880-1930</title>, Puvill Libros S.A. <year>1988</year><raw>Lopez, Ignacio-Javier:Caballero de Novela, Ensayo sobre el donjuanismo en la novela española moderna, 1880-1930, Puvill Libros S.A., 1988</raw></sequence><sequence><author><surname>Salper</surname>, <given-names>Roberta</given-names></author> <title>L.,Valle-Inclán y su mundo: ideología y forma narrativa</title>, <other>Rodopi, Amsterdam</other> <year>1988</year>.<raw>Salper, Roberta L.,Valle-Inclán y su mundo: ideología y forma narrativa, Rodopi, Amsterdam 1988.</raw></sequence><sequence><author><surname>Shaw</surname>, <given-names>Donald</given-names></author> <title>L.:The generation of 1898 in Spain,Ernest Benn Limited</title>, <other>London</other> <year>1975</year>.<raw>Shaw, Donald L.:The generation of 1898 in Spain,Ernest Benn Limited, London 1975.</raw></sequence>